
{"items":[{"name":"_208_Group_Project_Demo","href":"_208_Group_Project_Demo.html","topicHref":"_208_Group_Project_Demo.html","topicUid":"_208_Group_Project_Demo","type":"Namespace","items":[{"name":"Blackjack","href":"_208_Group_Project_Demo.Blackjack.html","topicHref":"_208_Group_Project_Demo.Blackjack.html","topicUid":"_208_Group_Project_Demo.Blackjack","type":"Class"},{"name":"BlackjackAction","href":"_208_Group_Project_Demo.BlackjackAction.html","topicHref":"_208_Group_Project_Demo.BlackjackAction.html","topicUid":"_208_Group_Project_Demo.BlackjackAction","type":"Enum"},{"name":"BlackjackResult","href":"_208_Group_Project_Demo.BlackjackResult.html","topicHref":"_208_Group_Project_Demo.BlackjackResult.html","topicUid":"_208_Group_Project_Demo.BlackjackResult","type":"Enum"},{"name":"BlackjackState","href":"_208_Group_Project_Demo.BlackjackState.html","topicHref":"_208_Group_Project_Demo.BlackjackState.html","topicUid":"_208_Group_Project_Demo.BlackjackState","type":"Enum"},{"name":"Card","href":"_208_Group_Project_Demo.Card.html","topicHref":"_208_Group_Project_Demo.Card.html","topicUid":"_208_Group_Project_Demo.Card","type":"Class"},{"name":"CardCounter","href":"_208_Group_Project_Demo.CardCounter.html","topicHref":"_208_Group_Project_Demo.CardCounter.html","topicUid":"_208_Group_Project_Demo.CardCounter","type":"Class"},{"name":"FrontEnd","href":"_208_Group_Project_Demo.FrontEnd.html","topicHref":"_208_Group_Project_Demo.FrontEnd.html","topicUid":"_208_Group_Project_Demo.FrontEnd","type":"Class"},{"name":"Rank","href":"_208_Group_Project_Demo.Rank.html","topicHref":"_208_Group_Project_Demo.Rank.html","topicUid":"_208_Group_Project_Demo.Rank","type":"Enum"},{"name":"Suit","href":"_208_Group_Project_Demo.Suit.html","topicHref":"_208_Group_Project_Demo.Suit.html","topicUid":"_208_Group_Project_Demo.Suit","type":"Enum"}]}],"memberLayout":"SamePage","pdf":true}
